LICENSE
README.md
setup.py
buffered_pipe/__init__.py
buffered_pipe/__version__.py
buffered_pipe/generic_pipe.py
buffered_pipe/static_pipe.py
buffered_pipe/utils.py
buffered_pipe.egg-info/PKG-INFO
buffered_pipe.egg-info/SOURCES.txt
buffered_pipe.egg-info/dependency_links.txt
buffered_pipe.egg-info/top_level.txt
cpp/generic_module.cpp
cpp/static_module.cpp